pctx_client/__init__.py
pctx_client/_client.py
pctx_client/_convert.py
pctx_client/_tool.py
pctx_client/_websocket_client.py
pctx_client/exceptions.py
pctx_client/models.py
pctx_client-0.1.1.dist-info/WHEEL
pctx_client-0.1.1.dist-info/METADATA
pctx_client-0.1.1.dist-info/RECORD
