Metadata-Version: 2.3
Name: pctx-client
Version: 0.1.1
Summary: Python client for using Code Mode via PCTX
Author: Elias Posen, Patrick Kelly
Author-email: Elias Posen <elias@posen.ch>, Patrick Kelly <pmkelly4444@gmail.com>
Requires-Dist: httpx>=0.28.1
Requires-Dist: pydantic>=2.7.2
Requires-Dist: websockets>=15.0.1
Requires-Dist: crewai>=1.6.1 ; extra == 'crewai'
Requires-Dist: langchain>=1.1.2 ; extra == 'langchain'
Requires-Dist: openai-agents>=0.6.2 ; extra == 'openai'
Requires-Dist: pydantic-ai>=0.0.14 ; extra == 'pydantic-ai'
Requires-Python: >=3.10, <3.14
Project-URL: Bug Tracker, https://github.com/portofcontext/pctx/issues
Project-URL: Documentation, https://pctx.readthedocs.io/en/latest/
Project-URL: Homepage, https://github.com/portofcontext/pctx
Project-URL: Source, https://github.com/portofcontext/pctx
Provides-Extra: crewai
Provides-Extra: langchain
Provides-Extra: openai
Provides-Extra: pydantic-ai
